sparkrouter/__init__.py
sparkrouter/version.py
sparkrouter/entry_points/__init__.py
sparkrouter/entry_points/base.py
sparkrouter/entry_points/container.py
sparkrouter/entry_points/databricks.py
sparkrouter/entry_points/glue.py
sparkrouter/job/__init__.py
sparkrouter/job/abstract_job.py
sparkrouter/job/abstract_job_factory.py
sparkrouter-0.2.1.dist-info/METADATA
sparkrouter-0.2.1.dist-info/WHEEL
sparkrouter-0.2.1.dist-info/licenses/LICENSE
sparkrouter-0.2.1.dist-info/RECORD
