Metadata-Version: 2.4
Name: sparkrouter
Version: 0.2.1
Summary: Platform-agnostic job routing framework for Spark ETL pipelines
Project-URL: Homepage, https://github.com/j2clark/sparkrouter
Project-URL: Documentation, https://j2clark.github.io/sparkrouter
Project-URL: Repository, https://github.com/j2clark/sparkrouter
Project-URL: Issues, https://github.com/j2clark/sparkrouter/issues
Author-email: Jamie Clark <j2clark@gmail.com>
License-Expression: Apache-2.0
License-File: LICENSE
Keywords: data-pipeline,databricks,dependency-injection,emr,etl,factory-pattern,glue,platform-agnostic,spark
Classifier: Development Status :: 4 - Beta
Classifier: Intended Audience :: Developers
Classifier: License :: OSI Approved :: Apache Software License
Classifier: Programming Language :: Python :: 3.9
Classifier: Programming Language :: Python :: 3.10
Classifier: Programming Language :: Python :: 3.11
Classifier: Programming Language :: Python :: 3.12
Classifier: Topic :: Software Development :: Libraries :: Application Frameworks
Requires-Python: >=3.9
Provides-Extra: all
Requires-Dist: boto3>=1.26; extra == 'all'
Requires-Dist: pyspark>=3.0; extra == 'all'
Provides-Extra: aws
Requires-Dist: boto3>=1.26; extra == 'aws'
Provides-Extra: dev
Requires-Dist: mypy>=1.0; extra == 'dev'
Requires-Dist: pytest-cov>=4.0; extra == 'dev'
Requires-Dist: pytest>=7.0; extra == 'dev'
Requires-Dist: ruff>=0.1.0; extra == 'dev'
Provides-Extra: docs
Requires-Dist: mkdocs-material>=9.0; extra == 'docs'
Requires-Dist: mkdocs>=1.5; extra == 'docs'
Requires-Dist: mkdocstrings[python]>=0.24; extra == 'docs'
Provides-Extra: spark
Requires-Dist: pyspark>=3.0; extra == 'spark'
